odoo/addons/project_timesheet_time_control/README.rst
odoo/addons/project_timesheet_time_control/__init__.py
odoo/addons/project_timesheet_time_control/__manifest__.py
odoo/addons/project_timesheet_time_control/hooks.py
odoo/addons/project_timesheet_time_control/i18n/ar.po
odoo/addons/project_timesheet_time_control/i18n/bg.po
odoo/addons/project_timesheet_time_control/i18n/bs.po
odoo/addons/project_timesheet_time_control/i18n/ca.po
odoo/addons/project_timesheet_time_control/i18n/cs.po
odoo/addons/project_timesheet_time_control/i18n/de.po
odoo/addons/project_timesheet_time_control/i18n/el.po
odoo/addons/project_timesheet_time_control/i18n/el_GR.po
odoo/addons/project_timesheet_time_control/i18n/en_GB.po
odoo/addons/project_timesheet_time_control/i18n/es.po
odoo/addons/project_timesheet_time_control/i18n/es_AR.po
odoo/addons/project_timesheet_time_control/i18n/es_CR.po
odoo/addons/project_timesheet_time_control/i18n/es_EC.po
odoo/addons/project_timesheet_time_control/i18n/es_MX.po
odoo/addons/project_timesheet_time_control/i18n/es_VE.po
odoo/addons/project_timesheet_time_control/i18n/et.po
odoo/addons/project_timesheet_time_control/i18n/fi.po
odoo/addons/project_timesheet_time_control/i18n/fr.po
odoo/addons/project_timesheet_time_control/i18n/fr_CA.po
odoo/addons/project_timesheet_time_control/i18n/fr_FR.po
odoo/addons/project_timesheet_time_control/i18n/gl.po
odoo/addons/project_timesheet_time_control/i18n/hr.po
odoo/addons/project_timesheet_time_control/i18n/hr_HR.po
odoo/addons/project_timesheet_time_control/i18n/hu.po
odoo/addons/project_timesheet_time_control/i18n/id.po
odoo/addons/project_timesheet_time_control/i18n/it.po
odoo/addons/project_timesheet_time_control/i18n/ja.po
odoo/addons/project_timesheet_time_control/i18n/ko.po
odoo/addons/project_timesheet_time_control/i18n/lt.po
odoo/addons/project_timesheet_time_control/i18n/lv.po
odoo/addons/project_timesheet_time_control/i18n/mk.po
odoo/addons/project_timesheet_time_control/i18n/mn.po
odoo11_addon_project_timesheet_time_control-11.0.1.2.0.99.dev10.dist-info/METADATA
odoo11_addon_project_timesheet_time_control-11.0.1.2.0.99.dev10.dist-info/WHEEL
odoo11_addon_project_timesheet_time_control-11.0.1.2.0.99.dev10.dist-info/top_level.txt
odoo11_addon_project_timesheet_time_control-11.0.1.2.0.99.dev10.dist-info/RECORD
